{
  "environment": "Freshdesk",
  "format": "html",
  "prefix": "https://storage.googleapis.com",
  "mainga": "UA-49880327-14",
  "updated": "2019-09-16T01:40:23Z",
  "id": "fh3",
  "duration": 0,
  "title": "4. Introduction to Serverless Apps",
  "authors": "Hemchander S",
  "summary": "The Freshworks app development platform includes a serverless environment to enable you to create apps that run in response to events that can originate from the Freshworks products, the app setup lifecycle, as well as events from any compatible service on the Internet.",
  "source": "1t3Y6jB-HWCI-d_lJulkmktFoENfPCBoZ5_4C0igmu_o",
  "theme": "web",
  "status": [
    "published"
  ],
  "category": [
    "Freshdesk"
  ],
  "tags": [
    "freshdesk"
  ],
  "feedback": "https://github.com/hemchander23/weatherbuddy",
  "url": "fh3"
}
